{
    "0": {
        "aliases": [],
        "id": 0,
        "stream": "in addition"
    },
    "1": {
        "aliases": [
            "there is"
        ],
        "id": 1,
        "stream": "there are"
    },
    "2": {
        "aliases": [
            "there\u2018s",
            "there\u2019s"
        ],
        "id": 2,
        "stream": "there's"
    },
    "3": {
        "aliases": [],
        "id": 3,
        "stream": "that"
    },
    "4": {
        "aliases": [],
        "id": 4,
        "stream": "together"
    },
    "5": {
        "aliases": [],
        "id": 5,
        "stream": "form"
    },
    "6": {
        "aliases": [],
        "id": 6,
        "stream": "can be"
    },
    "7": {
        "aliases": [],
        "id": 7,
        "stream": "accessed"
    },
    "8": {
        "aliases": [],
        "id": 8,
        "stream": "when"
    },
    "9": {
        "aliases": [],
        "id": 9,
        "stream": "upon"
    },
    "10": {
        "aliases": [],
        "id": 10,
        "stream": "bit"
    },
    "11": {
        "aliases": [],
        "id": 11,
        "stream": "of"
    },
    "12": {
        "aliases": [
            "are set"
        ],
        "id": 12,
        "stream": "is set"
    },
    "13": {
        "aliases": [],
        "id": 13,
        "stream": "to"
    },
    "14": {
        "aliases": [],
        "id": 14,
        "stream": "in"
    },
    "15": {
        "aliases": [],
        "id": 15,
        "stream": "above"
    },
    "16": {
        "aliases": [],
        "id": 16,
        "stream": "at"
    },
    "17": {
        "aliases": [
            "can\u2018t be",
            "can\u2019t be"
        ],
        "id": 17,
        "stream": "can't be"
    },
    "18": {
        "aliases": [
            "can't",
            "can\u2018t",
            "can\u2019t"
        ],
        "id": 18,
        "stream": "cannot"
    },
    "19": {
        "aliases": [],
        "id": 19,
        "stream": "does"
    },
    "20": {
        "aliases": [
            "doesn't",
            "doesn\u2019t",
            "doesn\u2018t"
        ],
        "id": 20,
        "stream": "does not"
    },
    "21": {
        "aliases": [],
        "id": 21,
        "stream": "using"
    },
    "22": {
        "aliases": [],
        "id": 22,
        "stream": "additional"
    },
    "23": {
        "aliases": [],
        "id": 23,
        "stream": "available"
    },
    "24": {
        "aliases": [],
        "id": 24,
        "stream": "for"
    },
    "25": {
        "aliases": [],
        "id": 25,
        "stream": "reset value"
    },
    "26": {
        "aliases": [],
        "id": 26,
        "stream": "to retrieve"
    },
    "27": {
        "aliases": [],
        "id": 27,
        "stream": "what is"
    },
    "28": {
        "aliases": [],
        "id": 28,
        "stream": "current"
    },
    "29": {
        "aliases": [],
        "id": 29,
        "stream": "following"
    },
    "30": {
        "aliases": [],
        "id": 30,
        "stream": "displays"
    },
    "31": {
        "aliases": [],
        "id": 31,
        "stream": "list of"
    },
    "32": {
        "aliases": [],
        "id": 32,
        "stream": "along with"
    },
    "33": {
        "aliases": [],
        "id": 33,
        "stream": "they"
    },
    "34": {
        "aliases": [],
        "id": 34,
        "stream": "enable"
    },
    "35": {
        "aliases": [],
        "id": 35,
        "stream": "priority"
    },
    "36": {
        "aliases": [],
        "id": 36,
        "stream": "their"
    },
    "37": {
        "aliases": [],
        "id": 37,
        "stream": "set"
    },
    "38": {
        "aliases": [],
        "id": 38,
        "stream": "disable"
    },
    "39": {
        "aliases": [],
        "id": 39,
        "stream": "from"
    },
    "40": {
        "aliases": [],
        "id": 40,
        "stream": "through"
    },
    "41": {
        "aliases": [],
        "id": 41,
        "stream": "["
    },
    "42": {
        "aliases": [],
        "id": 42,
        "stream": "]"
    },
    "43": {
        "aliases": [],
        "id": 43,
        "stream": ":"
    },
    "44": {
        "aliases": [
            "are equal to",
            "are set equal to",
            "is equal to",
            "is set equal to",
            "goes to"
        ],
        "id": 44,
        "stream": "is set to"
    },
    "45": {
        "aliases": [],
        "id": 45,
        "stream": "port"
    },
    "46": {
        "aliases": [
            "is an"
        ],
        "id": 46,
        "stream": "is a"
    },
    "47": {
        "aliases": [
            "has an"
        ],
        "id": 47,
        "stream": "has a"
    },
    "48": {
        "aliases": [],
        "id": 48,
        "stream": "has"
    },
    "49": {
        "aliases": [
            "are",
            "goes"
        ],
        "id": 49,
        "stream": "is"
    },
    "50": {
        "aliases": [],
        "id": 50,
        "stream": "if"
    },
    "51": {
        "aliases": [],
        "id": 51,
        "stream": "in progress"
    },
    "52": {
        "aliases": [],
        "id": 52,
        "stream": "ie"
    },
    "53": {
        "aliases": [],
        "id": 53,
        "stream": "then"
    },
    "54": {
        "aliases": [],
        "id": 54,
        "stream": ","
    },
    "55": {
        "aliases": [],
        "id": 55,
        "stream": "both"
    },
    "56": {
        "aliases": [],
        "id": 56,
        "stream": "read"
    },
    "57": {
        "aliases": [],
        "id": 57,
        "stream": "cleared"
    },
    "58": {
        "aliases": [],
        "id": 58,
        "stream": "ignored"
    },
    "59": {
        "aliases": [],
        "id": 59,
        "stream": "writing"
    },
    "60": {
        "aliases": [
            "an"
        ],
        "id": 60,
        "stream": "a"
    },
    "61": {
        "aliases": [],
        "id": 61,
        "stream": "reset"
    },
    "62": {
        "aliases": [],
        "id": 62,
        "stream": "but"
    },
    "63": {
        "aliases": [],
        "id": 63,
        "stream": "bit #"
    },
    "64": {
        "aliases": [],
        "id": 64,
        "stream": "and"
    },
    "65": {
        "aliases": [],
        "id": 65,
        "stream": "or"
    },
    "66": {
        "aliases": [],
        "id": 66,
        "stream": "."
    },
    "67": {
        "aliases": [],
        "id": 67,
        "stream": "can"
    },
    "68": {
        "aliases": [],
        "id": 68,
        "stream": "until"
    },
    "69": {
        "aliases": [
            "is required to be",
            "should be",
            "shall be",
            "must",
            "is required",
            "there must be"
        ],
        "id": 69,
        "stream": "must be"
    },
    "70": {
        "aliases": [],
        "id": 70,
        "stream": "on"
    },
    "71": {
        "aliases": [],
        "id": 71,
        "stream": "value"
    },
    "72": {
        "aliases": [],
        "id": 72,
        "stream": "after"
    },
    "73": {
        "aliases": [],
        "id": 73,
        "stream": "before"
    },
    "74": {
        "aliases": [],
        "id": 74,
        "stream": "during"
    },
    "75": {
        "aliases": [],
        "id": 75,
        "stream": "should"
    },
    "76": {
        "aliases": [],
        "id": 76,
        "stream": "should not"
    },
    "77": {
        "aliases": [
            "to be able to"
        ],
        "id": 77,
        "stream": "in order to"
    },
    "78": {
        "aliases": [],
        "id": 78,
        "stream": "to be"
    }
}